{"item": [[{"link": {"code": "DRQgVUCUOwxpHcEgEB9LIA==", "distance": 305, "line": [34.4619606, 133.1830794, 34.4620064, 133.1829114, 34.4620775, 133.182675, 34.4621436, 133.1824308, 34.4621994, 133.18224, 34.46222, 133.1821714, 34.4622353, 133.1820953, 34.4623014, 133.1818281, 34.4623675, 133.1814467, 34.4624233, 133.1811567, 34.4624692, 133.1808439, 34.4624944, 133.1805844, 34.462525, 133.1803403, 34.4625403, 133.1800811, 34.4625606, 133.1798522], "order": "OE", "roadType": {"code": "0", "text": "\u9ad8\u901f\u9053\u8def"}, "limitedHighway": true, "numberOfLanes": 2, "roadWidth": 2, "linkSeparation": true, "structure": null, "zlinkCode": 21027, "onewayCode": 1, "generalRoadName1": "\u5c71\u967d\u81ea\u52d5\u8eca\u9053", "generalRoadName2": null, "officialRoadName": null, "popularRoadName": null, "adas": {"stopInfoFront": null, "stopInfoBack": null, "maxspeedFront": [{"limit": 80, "start": 0, "end": 100}], "maxspeedBack": null, "accidentPointFront": null, "accidentPointBack": null, "limitinfoFront": null, "limitinfoBack": null, "directionSignFront": null, "directionSignBack": null, "roadelevation": [{"lat": 34.4619592, "lon": 133.1830853, "elevation": 93403}, {"lat": 34.4619711, "lon": 133.1830408, "elevation": 93376}, {"lat": 34.4619831, "lon": 133.1829967, "elevation": 93350}, {"lat": 34.4619947, "lon": 133.1829522, "elevation": 93323}, {"lat": 34.4620067, "lon": 133.1829078, "elevation": 93296}, {"lat": 34.4620183, "lon": 133.1828658, "elevation": 93273}, {"lat": 34.4620303, "lon": 133.1828239, "elevation": 93251}, {"lat": 34.4620419, "lon": 133.1827819, "elevation": 93228}, {"lat": 34.4620581, "lon": 133.1827253, "elevation": 93199}, {"lat": 34.4620739, "lon": 133.1826683, "elevation": 93171}, {"lat": 34.4620869, "lon": 133.1826211, "elevation": 93150}, {"lat": 34.4621003, "lon": 133.1825736, "elevation": 93128}, {"lat": 34.4621133, "lon": 133.1825264, "elevation": 93107}, {"lat": 34.4621267, "lon": 133.1824789, "elevation": 93086}, {"lat": 34.4621397, "lon": 133.1824317, "elevation": 93064}, {"lat": 34.4621536, "lon": 133.1823856, "elevation": 93045}, {"lat": 34.4621675, "lon": 133.1823392, "elevation": 93025}, {"lat": 34.4621814, "lon": 133.1822931, "elevation": 93006}, {"lat": 34.4621953, "lon": 133.1822467, "elevation": 92986}, {"lat": 34.4622056, "lon": 133.1822117, "elevation": 92980}, {"lat": 34.4622158, "lon": 133.1821764, "elevation": 92973}, {"lat": 34.4622256, "lon": 133.1821375, "elevation": 92966}, {"lat": 34.462235, "lon": 133.1820986, "elevation": 92958}, {"lat": 34.462245, "lon": 133.1820542, "elevation": 92958}, {"lat": 34.4622547, "lon": 133.1820094, "elevation": 92957}, {"lat": 34.4622697, "lon": 133.1819406, "elevation": 92919}, {"lat": 34.4622814, "lon": 133.1818878, "elevation": 92911}, {"lat": 34.4622928, "lon": 133.1818347, "elevation": 92903}, {"lat": 34.4623036, "lon": 133.1817775, "elevation": 92901}, {"lat": 34.4623142, "lon": 133.1817203, "elevation": 92899}, {"lat": 34.4623247, "lon": 133.1816656, "elevation": 92880}, {"lat": 34.462335, "lon": 133.1816106, "elevation": 92861}, {"lat": 34.462345, "lon": 133.1815572, "elevation": 92863}, {"lat": 34.4623553, "lon": 133.1815042, "elevation": 92864}, {"lat": 34.4623653, "lon": 133.1814508, "elevation": 92866}, {"lat": 34.462375, "lon": 133.1813944, "elevation": 92861}, {"lat": 34.4623847, "lon": 133.1813381, "elevation": 92856}, {"lat": 34.4623947, "lon": 133.1812817, "elevation": 92851}, {"lat": 34.4624044, "lon": 133.1812253, "elevation": 92846}, {"lat": 34.4624142, "lon": 133.1811689, "elevation": 92841}, {"lat": 34.4624219, "lon": 133.1811103, "elevation": 92845}, {"lat": 34.4624306, "lon": 133.1810481, "elevation": 92848}, {"lat": 34.4624389, "lon": 133.1809856, "elevation": 92852}, {"lat": 34.462445, "lon": 133.1809394, "elevation": 92868}, {"lat": 34.4624511, "lon": 133.1808933, "elevation": 92884}, {"lat": 34.4624572, "lon": 133.1808472, "elevation": 92900}, {"lat": 34.462465, "lon": 133.1807831, "elevation": 92917}, {"lat": 34.4624728, "lon": 133.1807189, "elevation": 92934}, {"lat": 34.4624783, "lon": 133.1806733, "elevation": 92956}, {"lat": 34.4624839, "lon": 133.1806275, "elevation": 92978}, {"lat": 34.4624894, "lon": 133.1805819, "elevation": 93000}, {"lat": 34.4624942, "lon": 133.1805383, "elevation": 93021}, {"lat": 34.4624992, "lon": 133.180495, "elevation": 93043}, {"lat": 34.4625039, "lon": 133.1804514, "elevation": 93064}, {"lat": 34.46251, "lon": 133.1803975, "elevation": 93099}, {"lat": 34.4625161, "lon": 133.1803436, "elevation": 93134}, {"lat": 34.4625206, "lon": 133.1802828, "elevation": 93164}, {"lat": 34.4625247, "lon": 133.1802219, "elevation": 93195}, {"lat": 34.4625281, "lon": 133.1801764, "elevation": 93229}, {"lat": 34.4625314, "lon": 133.1801306, "elevation": 93262}, {"lat": 34.4625347, "lon": 133.180085, "elevation": 93296}, {"lat": 34.4625389, "lon": 133.1800286, "elevation": 93333}, {"lat": 34.4625431, "lon": 133.1799719, "elevation": 93369}, {"lat": 34.4625469, "lon": 133.1799156, "elevation": 93406}, {"lat": 34.4625511, "lon": 133.1798589, "elevation": 93443}]}}, "closest": {"lat": 34.4625606, "lon": 133.1798528}, "distance": 0}, {"link": {"code": "DRQgVSKNOwxEHcEgaR3BIA==", "distance": 25, "line": [34.4625606, 133.1798522, 34.4625606, 133.1795697], "order": "OE", "roadType": {"code": "0", "text": "\u9ad8\u901f\u9053\u8def"}, "limitedHighway": true, "numberOfLanes": 1, "roadWidth": 1, "linkSeparation": false, "structure": null, "zlinkCode": 72047, "onewayCode": 1, "generalRoadName1": "\u5c71\u967d\u81ea\u52d5\u8eca\u9053", "generalRoadName2": null, "officialRoadName": null, "popularRoadName": null, "adas": {"stopInfoFront": null, "stopInfoBack": null, "maxspeedFront": [{"limit": 40, "start": 0, "end": 100}], "maxspeedBack": null, "accidentPointFront": null, "accidentPointBack": null, "limitinfoFront": null, "limitinfoBack": null, "directionSignFront": null, "directionSignBack": null, "roadelevation": [{"lat": 34.4625603, "lon": 133.1798522, "elevation": 93443}, {"lat": 34.46256, "lon": 133.1798019, "elevation": 93462}, {"lat": 34.46256, "lon": 133.1797517, "elevation": 93481}, {"lat": 34.4625597, "lon": 133.1797014, "elevation": 93500}, {"lat": 34.4625597, "lon": 133.1796511, "elevation": 93519}, {"lat": 34.4625594, "lon": 133.1796008, "elevation": 93538}, {"lat": 34.4625594, "lon": 133.1795669, "elevation": 93552}]}}, "closest": {"lat": 34.4625606, "lon": 133.1798522}, "distance": 0}, {"link": {"code": "DRQgVTWROwxEHcUgaR3BIA==", "distance": 26, "line": [34.4625606, 133.1798522, 34.4625811, 133.1795697], "order": "OE", "roadType": {"code": "0", "text": "\u9ad8\u901f\u9053\u8def"}, "limitedHighway": true, "numberOfLanes": 2, "roadWidth": 2, "linkSeparation": true, "structure": null, "zlinkCode": 21028, "onewayCode": 1, "generalRoadName1": "\u5c71\u967d\u81ea\u52d5\u8eca\u9053", "generalRoadName2": null, "officialRoadName": null, "popularRoadName": null, "adas": {"stopInfoFront": null, "stopInfoBack": null, "maxspeedFront": [{"limit": 80, "start": 0, "end": 100}], "maxspeedBack": null, "accidentPointFront": null, "accidentPointBack": null, "limitinfoFront": null, "limitinfoBack": null, "directionSignFront": null, "directionSignBack": null, "roadelevation": [{"lat": 34.4625603, "lon": 133.1798522, "elevation": 93443}, {"lat": 34.4625631, "lon": 133.1798019, "elevation": 93467}, {"lat": 34.4625661, "lon": 133.1797514, "elevation": 93491}, {"lat": 34.4625689, "lon": 133.1797011, "elevation": 93514}, {"lat": 34.4625719, "lon": 133.1796506, "elevation": 93538}, {"lat": 34.4625747, "lon": 133.1796003, "elevation": 93562}, {"lat": 34.4625767, "lon": 133.1795661, "elevation": 93590}]}}, "closest": {"lat": 34.4625606, "lon": 133.1798522}, "distance": 0}]]}